{
  "fecha_procesamiento": "2026-03-27T07:29:11.681354",
  "proveedores": [
    "PROINCO",
    "ELECTROSTOCK"
  ],
  "total_productos": 27,
  "datos": {
    "PROINCO": [],
    "ELECTROSTOCK": [
      {
        "ref": "403588",
        "descripcion": "36 B23788599",
        "precio": 1.0,
        "proveedor": "ELECTROSTOCK",
        "fecha_cotizacion": "2026-03-27"
      },
      {
        "ref": "403589",
        "descripcion": "jaen@grupoelectrostocks.com",
        "precio": 1.0,
        "proveedor": "ELECTROSTOCK",
        "fecha_cotizacion": "2026-03-27"
      },
      {
        "ref": "403590",
        "descripcion": "AFC RENOVABLES SL",
        "precio": 1.0,
        "proveedor": "ELECTROSTOCK",
        "fecha_cotizacion": "2026-03-27"
      },
      {
        "ref": "403612",
        "descripcion": "23006 JAEN",
        "precio": 1.0,
        "proveedor": "ELECTROSTOCK",
        "fecha_cotizacion": "2026-03-27"
      },
      {
        "ref": "403033",
        "descripcion": "100PCE",
        "precio": 1.0,
        "proveedor": "ELECTROSTOCK",
        "fecha_cotizacion": "2026-03-27"
      },
      {
        "ref": "411525",
        "descripcion": "MTR035_91032",
        "precio": 1.0,
        "proveedor": "ELECTROSTOCK",
        "fecha_cotizacion": "2026-03-27"
      },
      {
        "ref": "411506",
        "descripcion": "12.34DESCRIPCION UNIDADES PRECIO/U.P. DTO. IMPORTEGrupo Electro Stocks, S.L.U. - Camí de ca n'Ametller 16, 4ª planta - 08195 - Sant Cugat del Valles - B644718401 /.",
        "precio": 1.0,
        "proveedor": "ELECTROSTOCK",
        "fecha_cotizacion": "2026-03-27"
      },
      {
        "ref": "411526",
        "descripcion": "JOSE MANUEL DOMINGO LINDE",
        "precio": 1.0,
        "proveedor": "ELECTROSTOCK",
        "fecha_cotizacion": "2026-03-27"
      },
      {
        "ref": "403628",
        "descripcion": "PEDIDO",
        "precio": 1.0,
        "proveedor": "ELECTROSTOCK",
        "fecha_cotizacion": "2026-03-27"
      },
      {
        "ref": "403629",
        "descripcion": "CONTACTO:",
        "precio": 1.0,
        "proveedor": "ELECTROSTOCK",
        "fecha_cotizacion": "2026-03-27"
      },
      {
        "ref": "403630",
        "descripcion": "VALIDEZ OFERTA: 7 DÍASNETO",
        "precio": 1.0,
        "proveedor": "ELECTROSTOCK",
        "fecha_cotizacion": "2026-03-27"
      },
      {
        "ref": "403632",
        "descripcion": "ES JAÉN",
        "precio": 1.0,
        "proveedor": "ELECTROSTOCK",
        "fecha_cotizacion": "2026-03-27"
      },
      {
        "ref": "403005",
        "descripcion": "*MAGNET TX3 6KA C P+N 25A",
        "precio": 1.0,
        "proveedor": "ELECTROSTOCK",
        "fecha_cotizacion": "2026-03-27"
      },
      {
        "ref": "411665",
        "descripcion": "*MAGNET TX3 6KA C P+N 32A",
        "precio": 1.0,
        "proveedor": "ELECTROSTOCK",
        "fecha_cotizacion": "2026-03-27"
      },
      {
        "ref": "411662",
        "descripcion": "*MAGNET TX3 6KA C P+N 40A",
        "precio": 1.0,
        "proveedor": "ELECTROSTOCK",
        "fecha_cotizacion": "2026-03-27"
      },
      {
        "ref": "411666",
        "descripcion": "*MAGNET TX3 6KA C 2P 63A",
        "precio": 1.0,
        "proveedor": "ELECTROSTOCK",
        "fecha_cotizacion": "2026-03-27"
      },
      {
        "ref": "402057",
        "descripcion": "DIFERENCIAL TX3 2/40/30 AC",
        "precio": 1.0,
        "proveedor": "ELECTROSTOCK",
        "fecha_cotizacion": "2026-03-27"
      },
      {
        "ref": "419928",
        "descripcion": "DIFERENCIAL DX3 2/40/300 AC",
        "precio": 1.0,
        "proveedor": "ELECTROSTOCK",
        "fecha_cotizacion": "2026-03-27"
      },
      {
        "ref": "419929",
        "descripcion": "DIFERENCIAL DX3 2/63/30 AC",
        "precio": 1.0,
        "proveedor": "ELECTROSTOCK",
        "fecha_cotizacion": "2026-03-27"
      },
      {
        "ref": "419930",
        "descripcion": "DIFERENCIAL DX3 2/63/300 AC",
        "precio": 1.0,
        "proveedor": "ELECTROSTOCK",
        "fecha_cotizacion": "2026-03-27"
      },
      {
        "ref": "10002463",
        "descripcion": "MAGNET TX3 6KA C 4P 25A",
        "precio": 1.0,
        "proveedor": "ELECTROSTOCK",
        "fecha_cotizacion": "2026-03-27"
      },
      {
        "ref": "10002464",
        "descripcion": "MAGNET TX3 6KA C 4P 32A",
        "precio": 1.0,
        "proveedor": "ELECTROSTOCK",
        "fecha_cotizacion": "2026-03-27"
      },
      {
        "ref": "10003476",
        "descripcion": "MAGNET TX3 6KA C 4P 40A",
        "precio": 1.0,
        "proveedor": "ELECTROSTOCK",
        "fecha_cotizacion": "2026-03-27"
      },
      {
        "ref": "491630",
        "descripcion": "MAGNET TX3 6KA C 4P 63A",
        "precio": 1.0,
        "proveedor": "ELECTROSTOCK",
        "fecha_cotizacion": "2026-03-27"
      },
      {
        "ref": "485150",
        "descripcion": "DIFERENCIAL TX3 4/40/30 AC",
        "precio": 1.0,
        "proveedor": "ELECTROSTOCK",
        "fecha_cotizacion": "2026-03-27"
      },
      {
        "ref": "070500025",
        "descripcion": "DIFERENCIAL DX3 4/40/300 AC",
        "precio": 100.0,
        "proveedor": "ELECTROSTOCK",
        "fecha_cotizacion": "2026-03-27"
      },
      {
        "ref": "070500040",
        "descripcion": "DIFERENCIAL DX3 4/63/30 AC",
        "precio": 8.76,
        "proveedor": "ELECTROSTOCK",
        "fecha_cotizacion": "2026-03-27"
      }
    ]
  }
}